README.rst
setup.py
octoproxy/__init__.py
octoproxy.egg-info/PKG-INFO
octoproxy.egg-info/SOURCES.txt
octoproxy.egg-info/dependency_links.txt
octoproxy.egg-info/requires.txt
octoproxy.egg-info/top_level.txt