Metadata-Version: 1.1
Name: octoproxy
Version: 1.0
Summary: Proxy for Sidelaunching on GitHub Events
Home-page: https://github.com/mverteuil/octoproxy
Author: M. de Verteuil
Author-email: mverteuil@github.com
License: UNKNOWN
Platform: UNKNOWN
Classifier: Development Status :: 2 - Pre-Alpha
Classifier: Programming Language :: Python
Classifier: Programming Language :: Python :: 2
Classifier: Programming Language :: Python :: 2.7
Classifier: Programming Language :: Python :: 3
Classifier: Programming Language :: Python :: 3.4
